setup.py
morton/__init__.py
morton/example.py
morton/tests.py
morton.egg-info/PKG-INFO
morton.egg-info/SOURCES.txt
morton.egg-info/dependency_links.txt
morton.egg-info/entry_points.txt
morton.egg-info/top_level.txt
morton.egg-info/zip-safe