Metadata-Version: 1.1
Name: morton
Version: 0.9.0
Summary: convert x,y into a Z-Order number
